pyPDP/__init__.py
pyPDP/algorithms/__init__.py
pyPDP/algorithms/ice.py
pyPDP/algorithms/pdp.py
pyPDP/algorithms/partitioner/__init__.py
pyPDP/algorithms/partitioner/decision_tree_partitioner.py
pyPDP/algorithms/partitioner/random_forest_partitioner.py
pyPDP/blackbox_functions/__init__.py
pyPDP/blackbox_functions/hpo_bench.py
pyPDP/blackbox_functions/synthetic_functions.py
pyPDP/sampler/__init__.py
pyPDP/sampler/acquisition_function.py
pyPDP/sampler/bayesian_optimization.py
pyPDP/sampler/grid_sampler.py
pyPDP/sampler/random_sampler.py
pyPDP/surrogate_models/__init__.py
pyPDP/surrogate_models/sklearn_surrogates.py
pyPDP/utils/__init__.py
pyPDP/utils/advanced_plots.py
pyPDP/utils/plotting.py
pyPDP/utils/typing.py
pyPDP/utils/utils.py
pyPDPPartitioner-0.1.9.dist-info/LICENSE
pyPDPPartitioner-0.1.9.dist-info/METADATA
pyPDPPartitioner-0.1.9.dist-info/WHEEL
pyPDPPartitioner-0.1.9.dist-info/top_level.txt
pyPDPPartitioner-0.1.9.dist-info/RECORD
