Metadata-Version: 2.1
Name: pyPDPPartitioner
Version: 0.1.9
Summary: A python implementation of 'Explaining Hyperparameter Optimization via Partial Dependence Plots' by Moosbauer et al.
Home-page: https://github.com/dwoiwode/py-pdp-partitioner
Author: Yannik Mahlau and Dominik Woiwode
Author-email: woiwode@tnt.uni-hannover.de
License: Apache-2.0
Platform: Windows
Platform: Linux
Classifier: Programming Language :: Python :: 3.8
Classifier: Programming Language :: Python :: 3.9
Classifier: Programming Language :: Python :: 3.10
Classifier: Development Status :: 3 - Alpha
Classifier: Natural Language :: English
Classifier: Environment :: Console
Classifier: Intended Audience :: Developers
Classifier: Intended Audience :: Education
Classifier: Intended Audience :: Science/Research
Classifier: License :: OSI Approved :: Apache Software License
Classifier: Operating System :: POSIX :: Linux
Classifier: Topic :: Scientific/Engineering :: Artificial Intelligence
Classifier: Topic :: Scientific/Engineering
Requires-Python: >=3.8
License-File: LICENSE
Requires-Dist: configspace >=0.7.1
Requires-Dist: matplotlib >=3.5.1
Requires-Dist: numpy >=1.22.0
Requires-Dist: scipy >=1.7.1
Requires-Dist: scikit-learn >=1.0
Requires-Dist: tqdm >=4.62.3
Provides-Extra: dev
Requires-Dist: pytest >=6.2.5 ; extra == 'dev'
Requires-Dist: pytest-cov >=3.0.0 ; extra == 'dev'
Provides-Extra: examples
Requires-Dist: pandas >=1.3.5 ; extra == 'examples'
Requires-Dist: openml ==0.12.2 ; extra == 'examples'
Provides-Extra: test
Requires-Dist: pytest >=6.2.5 ; extra == 'test'
Requires-Dist: pytest-cov >=3.0.0 ; extra == 'test'
Requires-Dist: pandas >=1.3.5 ; extra == 'test'
Requires-Dist: openml ==0.12.2 ; extra == 'test'
